Metadata-Version: 2.1
Name: stuffpy
Version: 0.0.1
Summary: A package for stuff
Home-page: UNKNOWN
Author: Zalman Belinow
Author-email: zalmanbelinow@gmail.com
License: UNKNOWN
Platform: UNKNOWN
Classifier: Programming Language :: Python :: 3
Classifier: License :: OSI Approved :: MIT License
Classifier: Operating System :: OS Independent
Requires-Python: >=3.10
License-File: LICENSE
